docker_bash_volume_watcher-1.0.8.dist-info/DESCRIPTION.rst
docker_bash_volume_watcher-1.0.8.dist-info/METADATA
docker_bash_volume_watcher-1.0.8.dist-info/RECORD
docker_bash_volume_watcher-1.0.8.dist-info/WHEEL
docker_bash_volume_watcher-1.0.8.dist-info/entry_points.txt
docker_bash_volume_watcher-1.0.8.dist-info/metadata.json
docker_bash_volume_watcher-1.0.8.dist-info/top_level.txt
docker_volume_watcher/__init__.py
docker_volume_watcher/cli.py
docker_volume_watcher/container_monitor.py
docker_volume_watcher/container_notifier.py
