Metadata-Version: 2.0
Name: docker-bash-volume-watcher
Version: 1.0.8
Summary: A tool to notify Docker contianers about changes in mounts on Bash for Windows.
Home-page: https://github.com/Kaptard/docker-bash-volume-watcher
Author: Kilian Volb, Mikhail Erofeev
Author-email: kilian@nexus-stats.com
License: MIT
Keywords: Docker volume Windows watch inotify
Platform: UNKNOWN
Classifier: Intended Audience :: Developers
Classifier: Operating System :: Microsoft :: Windows
Classifier: License :: OSI Approved :: MIT License
Classifier: Programming Language :: Python :: 2.7
Classifier: Programming Language :: Python :: 3
Classifier: Topic :: Software Development
Classifier: Topic :: System :: Monitoring
Requires-Dist: docker (==2.7.0)
Requires-Dist: watchdog (>=0.8.3)
